{
	"7.20.7": {
		"linux-arm64": {
			"conclusion": "pass",
			"date": "2026-07-05T05:19:25.297Z",
			"run_id": "28729947250"
		},
		"linux-x86": {
			"conclusion": "pass",
			"date": "2026-07-05T05:11:09.584Z",
			"run_id": "28729947250"
		}
	},
	"7.20.8": {
		"linux-arm64": {
			"conclusion": "pass",
			"date": "2026-07-05T05:19:25.297Z",
			"run_id": "28729947250"
		},
		"linux-x86": {
			"conclusion": "pass",
			"date": "2026-07-05T05:11:09.584Z",
			"run_id": "28729947250"
		}
	},
	"7.21.4": {
		"linux-x86": {
			"conclusion": "pass",
			"date": "2026-07-05T03:17:01.620Z",
			"run_id": "28727550832"
		}
	},
	"7.23.1": {
		"linux-arm64": {
			"conclusion": "pass",
			"date": "2026-07-05T05:19:25.297Z",
			"run_id": "28729947250"
		},
		"linux-x86": {
			"conclusion": "pass",
			"date": "2026-07-05T05:11:09.584Z",
			"run_id": "28729947250"
		}
	},
	"7.24beta3": {
		"linux-x86": {
			"conclusion": "pass",
			"date": "2026-07-05T03:19:54.891Z",
			"run_id": "28727545681"
		}
	},
	"7.24rc1": {
		"linux-x86": {
			"conclusion": "pass",
			"date": "2026-07-05T03:16:42.488Z",
			"run_id": "28727548584"
		}
	}
}
